dagster_dingtalk/__init__.py
dagster_dingtalk/app_client.py
dagster_dingtalk/operations.py
dagster_dingtalk/py.typed
dagster_dingtalk/resources.py
dagster_dingtalk/utils.py
dagster_dingtalk/version.py
dagster_dingtalk-0.28.12.dist-info/METADATA
dagster_dingtalk-0.28.12.dist-info/WHEEL
dagster_dingtalk-0.28.12.dist-info/RECORD
