Metadata-Version: 2.4
Name: dagster-dingtalk
Version: 0.28.12
Summary: A dagster plugin for the DingTalk
Author-email: YiZixuan <sqkkyzx@qq.com>
Requires-Python: >=3.13
Requires-Dist: dagster>=1.12.0
Requires-Dist: hatchling>=1.27.0
Requires-Dist: httpx
